{"cameraMode":{"drawMode":0,"name":"Shaded","section":"Shading Mode"},"sceneLighting":true,"audioPlay":false,"sceneViewState":{"m_AlwaysRefresh":false,"showFog":true,"showSkybox":true,"showFlares":true,"showImageEffects":true,"showParticleSystems":true,"showVisualEffectGraphs":true,"m_FxEnabled":true},"in2DMode":false,"pivot":{"x":-3.017453670501709,"y":1.3307619094848633,"z":-4.283437252044678},"rotation":{"x":0.012475088238716126,"y":-0.9847983121871948,"z":0.07994385808706284,"w":0.1536724716424942},"size":4.447444438934326,"orthographic":false}